WebVisCrawlerManager.py
WebVisCrawlerProcess.py
app.py
vis.py
webviscrawl-0.0.1.dist-info/METADATA
webviscrawl-0.0.1.dist-info/WHEEL
webviscrawl-0.0.1.dist-info/entry_points.txt
webviscrawl-0.0.1.dist-info/top_level.txt
webviscrawl-0.0.1.dist-info/RECORD
