Metadata-Version: 2.4
Name: WebVisCrawl
Version: 0.0.1
Summary: A web visualization and crawling tool
Author-email: Adithiya Venkatakrishnan <adithiya.venkatakrishnan@atomtables.dev>
Requires-Python: >=3.9
